jupyterlab_broccoli_turtle/__init__.py
jupyterlab_broccoli_turtle/_version.py
jupyterlab_broccoli_turtle/labextension/build_log.json
jupyterlab_broccoli_turtle/labextension/package.json
jupyterlab_broccoli_turtle/labextension/static/lib_index_js.b2dcc64b07f6a94c8ea6.js
jupyterlab_broccoli_turtle/labextension/static/lib_index_js.b2dcc64b07f6a94c8ea6.js.map
jupyterlab_broccoli_turtle/labextension/static/lib_msg_En_js.f514b8f10e0e961485a9.js
jupyterlab_broccoli_turtle/labextension/static/lib_msg_En_js.f514b8f10e0e961485a9.js.map
jupyterlab_broccoli_turtle/labextension/static/lib_msg_Jp_js.65036afd3c9657255125.js
jupyterlab_broccoli_turtle/labextension/static/lib_msg_Jp_js.65036afd3c9657255125.js.map
jupyterlab_broccoli_turtle/labextension/static/node_modules_jupyterlab-broccoli_lib_msg_En_js.c8204af4475dfbc16b34.js
jupyterlab_broccoli_turtle/labextension/static/node_modules_jupyterlab-broccoli_lib_msg_En_js.c8204af4475dfbc16b34.js.map
jupyterlab_broccoli_turtle/labextension/static/node_modules_jupyterlab-broccoli_lib_msg_Jp_js.58c76de77b244a11b5ea.js
jupyterlab_broccoli_turtle/labextension/static/node_modules_jupyterlab-broccoli_lib_msg_Jp_js.58c76de77b244a11b5ea.js.map
jupyterlab_broccoli_turtle/labextension/static/node_modules_jupyterlab-broccoli_lib_msg_lazy_recursive_js_-_f9570.1fdf99357f7588fb8923.js
jupyterlab_broccoli_turtle/labextension/static/node_modules_jupyterlab-broccoli_lib_msg_lazy_recursive_js_-_f9570.1fdf99357f7588fb8923.js.map
jupyterlab_broccoli_turtle/labextension/static/node_modules_jupyterlab-broccoli_lib_msg_lazy_recursive_js_-_f9571.b75783c9615182046d89.js
jupyterlab_broccoli_turtle/labextension/static/node_modules_jupyterlab-broccoli_lib_msg_lazy_recursive_js_-_f9571.b75783c9615182046d89.js.map
jupyterlab_broccoli_turtle/labextension/static/remoteEntry.bc6b247caa82d2f37189.js
jupyterlab_broccoli_turtle/labextension/static/remoteEntry.bc6b247caa82d2f37189.js.map
jupyterlab_broccoli_turtle/labextension/static/style.js
jupyterlab_broccoli_turtle-0.4.7.dist-info/METADATA
jupyterlab_broccoli_turtle-0.4.7.dist-info/WHEEL
jupyterlab_broccoli_turtle-0.4.7.dist-info/licenses/LICENSE
jupyterlab_broccoli_turtle-0.4.7.dist-info/RECORD
