Metadata-Version: 2.3
Name: jupyterlab-broccoli-turtle
Version: 0.4.7
Dynamic: Keywords
Summary: Simple Turtle Blocks of Blockly extension for JupyterLab.
Project-URL: Homepage, https://github.com/FumiHax/jupyterlab-broccoli-turtle
Project-URL: Bug Tracker, https://github.com/FumiHax/jupyterlab-broccoli-turtle/issues
Project-URL: Repository, https://github.com/FumiHax/jupyterlab-broccoli-turtle.git
Author-email: "Fumi.Iseki" <iseki@rsch.tuis.ac.jp>
License: BSD 3-Clause License
License-File: LICENSE
Classifier: Framework :: Jupyter
Classifier: Framework :: Jupyter :: JupyterLab
Classifier: Framework :: Jupyter :: JupyterLab :: 3
Classifier: Framework :: Jupyter :: JupyterLab :: Extensions
Classifier: Framework :: Jupyter :: JupyterLab :: Extensions :: Prebuilt
Classifier: License :: OSI Approved :: BSD License
Classifier: Programming Language :: Python
Classifier: Programming Language :: Python :: 3
Classifier: Programming Language :: Python :: 3.7
Classifier: Programming Language :: Python :: 3.8
Classifier: Programming Language :: Python :: 3.9
Classifier: Programming Language :: Python :: 3.10
Classifier: Programming Language :: Python :: 3.11
Requires-Python: >=3.7
Requires-Dist: jupyterlab-broccoli>=0.4.6
